swane/__init__.py
swane/__main__.py
swane/strings.py
swane/config/ConfigManager.py
swane/config/PrefCategory.py
swane/config/PreferenceEntry.py
swane/config/__init__.py
swane/config/config_enums.py
swane/config/preference_list.py
swane/nipype_pipeline/MainWorkflow.py
swane/nipype_pipeline/__init__.py
swane/nipype_pipeline/engine/CustomWorkflow.py
swane/nipype_pipeline/engine/MonitoredMultiProcPlugin.py
swane/nipype_pipeline/engine/NodeListEntry.py
swane/nipype_pipeline/engine/WorkflowReport.py
swane/nipype_pipeline/engine/__init__.py
swane/nipype_pipeline/nodes/AsymmetryIndex.py
swane/nipype_pipeline/nodes/CropFov.py
swane/nipype_pipeline/nodes/CustomDcm2niix.py
swane/nipype_pipeline/nodes/CustomEddy.py
swane/nipype_pipeline/nodes/CustomLabel2Vol.py
swane/nipype_pipeline/nodes/CustomProbTrackX2.py
swane/nipype_pipeline/nodes/CustomSliceTimer.py
swane/nipype_pipeline/nodes/DeleteVolumes.py
swane/nipype_pipeline/nodes/FLAT1OutliersMask.py
swane/nipype_pipeline/nodes/FMRIGenSpec.py
swane/nipype_pipeline/nodes/ForceOrient.py
swane/nipype_pipeline/nodes/FslNVols.py
swane/nipype_pipeline/nodes/GenEddyFiles.py
swane/nipype_pipeline/nodes/GetNiftiTR.py
swane/nipype_pipeline/nodes/MergeTargets.py
swane/nipype_pipeline/nodes/Orient.py
swane/nipype_pipeline/nodes/RandomSeedGenerator.py
swane/nipype_pipeline/nodes/SegmentHA.py
swane/nipype_pipeline/nodes/SumMultiTracks.py
swane/nipype_pipeline/nodes/SumMultiVols.py
swane/nipype_pipeline/nodes/TTest.py
swane/nipype_pipeline/nodes/ThrROI.py
swane/nipype_pipeline/nodes/VenousCheck.py
swane/nipype_pipeline/nodes/Zscore.py
swane/nipype_pipeline/nodes/__init__.py
swane/nipype_pipeline/nodes/utils.py
swane/nipype_pipeline/workflows/__init__.py
swane/nipype_pipeline/workflows/dti_preproc_workflow.py
swane/nipype_pipeline/workflows/flat1_workflow.py
swane/nipype_pipeline/workflows/freesurfer_asymmetry_index_workflow.py
swane/nipype_pipeline/workflows/freesurfer_workflow.py
swane/nipype_pipeline/workflows/func_map_workflow.py
swane-0.1.5.2.dist-info/licenses/LICENSE
swane-0.1.5.2.dist-info/METADATA
swane-0.1.5.2.dist-info/WHEEL
swane-0.1.5.2.dist-info/entry_points.txt
swane-0.1.5.2.dist-info/top_level.txt
swane-0.1.5.2.dist-info/RECORD
