Metadata-Version: 2.4
Name: swane
Version: 0.1.5.2
Summary: Standardized Workflow for Advanced Neuroimaging in Epilepsy
Author: LICE - Commissione Neuroimmagini
Author-email: dev@lice.it
License: MIT
Classifier: Programming Language :: Python :: 3
Classifier: License :: OSI Approved :: MIT License
Classifier: Operating System :: MacOS
Classifier: Operating System :: POSIX :: Linux
Requires-Python: >=3.10
License-File: LICENSE
Requires-Dist: networkx==3.4.2
Requires-Dist: nipype==1.10.0
Requires-Dist: PySide6
Requires-Dist: pydicom==3.0.1
Requires-Dist: configparser<=7.1.0
Requires-Dist: psutil==7.0.0
Requires-Dist: swane_supplement>=0.1.2
Requires-Dist: matplotlib==3.10.1
Requires-Dist: nibabel<6,>=5.3.0
Requires-Dist: packaging
Requires-Dist: PySide6_VerticalQTabWidget==0.0.3
Requires-Dist: numpy==2.2.4
Requires-Dist: cryptography
Requires-Dist: dicom-sequence-classifier==1.0.4
Dynamic: author
Dynamic: author-email
Dynamic: classifier
Dynamic: license
Dynamic: license-file
Dynamic: requires-dist
Dynamic: requires-python
Dynamic: summary
